{
  "node": {
    "002720c4ca9fd3c4503936f3196d2d3a7b93ff846c": {
      "workers": {
        "app/page": {
          "moduleId": "[project]/.next-internal/server/app/page/actions.js { ACTIONS_MODULE0 => \"[project]/actions/auth.ts [app-rsc] (ecmascript)\" } [app-rsc] (ecmascript)",
          "async": false
        }
      },
      "layer": {
        "app/page": "rsc"
      }
    },
    "00fa48169683651625007b8f8a251f0c4b308578e6": {
      "workers": {
        "app/page": {
          "moduleId": "[project]/.next-internal/server/app/page/actions.js { ACTIONS_MODULE0 => \"[project]/actions/auth.ts [app-rsc] (ecmascript)\" } [app-rsc] (ecmascript)",
          "async": false
        }
      },
      "layer": {
        "app/page": "rsc"
      }
    }
  },
  "edge": {}
}